MANIFEST.in
README.md
setup.py
docs/AUTHORS
docs/CHANGELOG.txt
docs/LICENSE
psu_site/__init__.py